sktest/__init__.py
sktest/run.py
sktest/common/__init__.py
sktest/common/acction.py
sktest/common/config.py
sktest/common/elements.py
sktest/common/email.py
sktest/common/globals.py
sktest/common/img.py
sktest/common/locator.py
sktest/common/log.py
sktest/common/ocr.py
sktest/common/report.py
sktest/common/snapshot.py
sktest/common/utility.py
sktest/sktest/__init__.py
sktest/sktest/autotest.py
sktest/sktest/testcase.py
sktest/sktest/testsuit.py
sktest-0.0.1.dist-info/LICENSE
sktest-0.0.1.dist-info/METADATA
sktest-0.0.1.dist-info/WHEEL
sktest-0.0.1.dist-info/top_level.txt
sktest-0.0.1.dist-info/RECORD
