Metadata-Version: 2.1
Name: sktest
Version: 0.0.1
Summary: A library of tools to quickly expand UI testing
Home-page: https://github.com/cxyboy/sktest
Author: xuluocan
Author-email: hijackx@163.com
License: UNKNOWN
Platform: UNKNOWN
Classifier: Programming Language :: Python :: 3
Classifier: License :: OSI Approved :: MIT License
Classifier: Operating System :: OS Independent
Requires-Python: >=3.6
